LICENSE
README.md
setup.py
treestructure/__init__.py
treestructure/binaryHeap.py
treestructure/binaryHeapNode.py
treestructure/binaryNode.py
treestructure/binarySearchTree.py
treestructure/constants.py
treestructure/version.py
treestructure.egg-info/PKG-INFO
treestructure.egg-info/SOURCES.txt
treestructure.egg-info/dependency_links.txt
treestructure.egg-info/top_level.txt