Metadata-Version: 2.1
Name: treestructure
Version: 1.0.0
Summary: Tree Structure is a module that implements some common trees in data structure.
Home-page: https://github.com/Musicmathstudio/treeStructure
Author: Tony Chiu
Author-email: pi3141592676@yahoo.com.tw
License: UNKNOWN
Keywords: tree structure,data structure
Platform: UNKNOWN
Classifier: License :: OSI Approved :: Apache Software License
Classifier: Topic :: Software Development :: Libraries :: Python Modules
Classifier: Operating System :: OS Independent
Classifier: Programming Language :: Python :: 3
Requires-Python: >=3
